bbot_server/__init__.py
bbot_server/agent/__init__.py
bbot_server/agent/agent.py
bbot_server/api/__init__.py
bbot_server/api/app.py
bbot_server/applets/__init__.py
bbot_server/applets/_base.py
bbot_server/applets/_root.py
bbot_server/applets/_routing.py
bbot_server/applets/activity.py
bbot_server/applets/agents/__init__.py
bbot_server/applets/agents/agents.py
bbot_server/applets/assets.py
bbot_server/applets/cloud.py
bbot_server/applets/discord.py
bbot_server/applets/dns_links.py
bbot_server/applets/emails.py
bbot_server/applets/events.py
bbot_server/applets/export.py
bbot_server/applets/findings.py
bbot_server/applets/open_ports.py
bbot_server/applets/redirects.py
bbot_server/applets/risk.py
bbot_server/applets/scans/scan_runs.py
bbot_server/applets/scans/scans.py
bbot_server/applets/scans/yara_rules.py
bbot_server/applets/stats.py
bbot_server/applets/targets.py
bbot_server/applets/technologies.py
bbot_server/applets/urls.py
bbot_server/applets/web_screenshots.py
bbot_server/assets/__init__.py
bbot_server/assets/custom_fields.py
bbot_server/cli/__init__.py
bbot_server/cli/activityctl.py
bbot_server/cli/agentctl.py
bbot_server/cli/assetctl.py
bbot_server/cli/base.py
bbot_server/cli/bbctl.py
bbot_server/cli/common.py
bbot_server/cli/eventctl.py
bbot_server/cli/scanctl.py
bbot_server/cli/scanrunsctl.py
bbot_server/cli/serverctl.py
bbot_server/cli/targetctl.py
bbot_server/cli/themes.py
bbot_server/config/__init__.py
bbot_server/connectionmanager.py
bbot_server/db/base.py
bbot_server/default_agent.sh
bbot_server/defaults.yml
bbot_server/defaults_docker.yml
bbot_server/errors.py
bbot_server/event_store/__init__.py
bbot_server/event_store/_base.py
bbot_server/event_store/mongo.py
bbot_server/interfaces/__init__.py
bbot_server/interfaces/base.py
bbot_server/interfaces/http.py
bbot_server/interfaces/python.py
bbot_server/logger.py
bbot_server/message_queue/__init__.py
bbot_server/message_queue/base.py
bbot_server/message_queue/nats.py.bak
bbot_server-0.1.0.dist-info/LICENSE
bbot_server-0.1.0.dist-info/METADATA
bbot_server-0.1.0.dist-info/WHEEL
bbot_server-0.1.0.dist-info/entry_points.txt
bbot_server-0.1.0.dist-info/RECORD
